mklsgit
